{
  "excluded": [
    {
      "value": "node_modules",
      "type": "path"
    },
    {
      "value": "proxy-agent",
      "type": "path"
    },
    {
      "value": "agent-base",
      "type": "path"
    },
    {
      "value": "http",
      "type": "path"
    },
    {
      "value": "lru-cache",
      "type": "path"
    },
    {
      "value": "net",
      "type": "path"
    },
    {
      "value": "tls",
      "type": "path"
    },
    {
      "value": "stream",
      "type": "path"
    },
    {
      "value": "pac-proxy-agent",
      "type": "path"
    },
    {
      "value": "url",
      "type": "path"
    },
    {
      "value": "http-proxy-agent",
      "type": "path"
    },
    {
      "value": "https-proxy-agent",
      "type": "path"
    },
    {
      "value": "KeySet",
      "type": "type"
    },
    {
      "value": "Payload",
      "type": "type"
    },
    {
      "value": "Query",
      "type": "type"
    },
    {
      "value": "",
      "type": "function"
    }
  ]
}